{
  "name": "[W11] BGM 정밀 식별 (yt-dlp 추출 + AudD 음향 지문 매칭)",
  "nodes": [
    {
      "parameters": {
        "httpMethod": "POST",
        "path": "bgm-identify",
        "responseMode": "lastNode",
        "options": {}
      },
      "id": "node-webhook-bgm",
      "name": "Webhook 수신",
      "type": "n8n-nodes-base.webhook",
      "typeVersion": 2,
      "position": [
        100,
        200
      ],
      "webhookId": "bgm-identify-webhook"
    },
    {
      "parameters": {},
      "id": "node-manual-bgm",
      "name": "수동 실행",
      "type": "n8n-nodes-base.manualTrigger",
      "typeVersion": 1,
      "position": [
        100,
        380
      ]
    },
    {
      "parameters": {
        "jsCode": "let url = '';\nlet clipSeconds = 20;\ntry {\n  const wh = $('Webhook 수신').all();\n  if (wh.length) {\n    const raw = wh[0].json;\n    const b = raw.body ?? raw;\n    const parsed = typeof b === 'string' ? JSON.parse(b) : b;\n    if (parsed?.url) url = String(parsed.url).trim();\n    if (parsed?.clipSeconds != null) clipSeconds = Math.max(5, Math.min(25, Number(parsed.clipSeconds) || 20));\n  }\n} catch {}\n// 테스트(수동 실행)용 기본 URL\nif (!url) url = 'https://www.youtube.com/shorts/cnVzHVTfhXE';\n\nconst executionId = ($execution && $execution.id) ? String($execution.id) : String(Date.now());\nconst clipPath = `/tmp/bgm-clip-${executionId}`;\n\nreturn [{ json: { url, clipSeconds, clipPath, source: 'n8n' } }];"
      },
      "id": "node-parse-params-bgm",
      "name": "파라미터 파싱",
      "type": "n8n-nodes-base.code",
      "typeVersion": 2,
      "position": [
        320,
        290
      ]
    },
    {
      "parameters": {
        "command": "=find /tmp -maxdepth 1 -name 'bgm-clip-*' -mmin +10 -delete 2>/dev/null; yt-dlp -f bestaudio --no-playlist -x --audio-format mp3 --download-sections \"*0-{{ $json.clipSeconds }}\" -o \"{{ $json.clipPath }}.%(ext)s\" \"{{ $json.url }}\""
      },
      "id": "node-extract-audio",
      "name": "오디오 클립 추출 (yt-dlp+ffmpeg)",
      "type": "n8n-nodes-base.executeCommand",
      "typeVersion": 1,
      "position": [
        540,
        190
      ],
      "onError": "continueErrorOutput"
    },
    {
      "parameters": {
        "filePath": "={{ $('파라미터 파싱').first().json.clipPath }}.mp3",
        "dataPropertyName": "data",
        "options": {}
      },
      "id": "node-read-clip",
      "name": "오디오 파일 읽기",
      "type": "n8n-nodes-base.readBinaryFile",
      "typeVersion": 1,
      "position": [
        760,
        110
      ],
      "onError": "continueErrorOutput"
    },
    {
      "parameters": {
        "method": "POST",
        "url": "https://api.audd.io/",
        "sendBody": true,
        "contentType": "multipart-form-data",
        "bodyParameters": {
          "parameters": [
            {
              "parameterType": "formBinaryData",
              "name": "file",
              "inputDataFieldName": "data"
            },
            {
              "parameterType": "formData",
              "name": "api_token",
              "value": "={{ $env.AUDD_API_TOKEN }}"
            },
            {
              "parameterType": "formData",
              "name": "return",
              "value": "spotify,apple_music"
            }
          ]
        },
        "options": {
          "timeout": 60000
        }
      },
      "id": "node-audd-call",
      "name": "AudD: 음향 지문 매칭",
      "type": "n8n-nodes-base.httpRequest",
      "typeVersion": 4.2,
      "position": [
        980,
        110
      ],
      "onError": "continueErrorOutput"
    },
    {
      "parameters": {
        "jsCode": "const params = $('파라미터 파싱').first().json;\nconst audd = $input.first().json;\n\nlet track = null;\nlet message = '';\n\nif (!audd || typeof audd !== 'object') {\n  message = 'AudD 응답을 받지 못했습니다. AUDD_API_TOKEN 환경변수와 네트워크 상태를 확인하세요.';\n} else if (audd.status === 'error') {\n  const code = audd?.error?.error_code;\n  const errMsg = audd?.error?.error_message || 'AudD API 오류';\n  message = code === 901 || code === 900\n    ? `AudD 인증 실패: ${errMsg} — n8n 컨테이너의 AUDD_API_TOKEN 값을 확인하세요.`\n    : `AudD 인식 실패: ${errMsg}`;\n} else {\n  const r = audd.result;\n  if (r && r.title) {\n    track = {\n      title: String(r.title),\n      artist: r.artist ? String(r.artist) : undefined,\n      album: r.album ? String(r.album) : undefined,\n      releaseDate: r.release_date ? String(r.release_date) : undefined,\n      label: r.label ? String(r.label) : undefined,\n      links: {\n        spotify: r.spotify?.external_urls?.spotify || undefined,\n        appleMusic: r.apple_music?.url || undefined,\n      },\n      source: 'audd',\n    };\n    message = `'${track.title}'${track.artist ? ` - ${track.artist}` : ''} 식별 완료 (AudD 음향 지문 매칭 — 추정이 아닌 실제 매칭 결과)`;\n  } else {\n    message = 'AudD DB에서 일치하는 곡을 찾지 못했습니다 (미등록 곡이거나 클립 구간에 BGM이 약하게 섞여 있을 수 있음).';\n  }\n}\n\nreturn [{ json: {\n  ok: true,\n  mode: 'n8n-audd',\n  url: params.url,\n  track,\n  message,\n} }];"
      },
      "id": "node-audd-parse",
      "name": "AudD 결과 파싱",
      "type": "n8n-nodes-base.code",
      "typeVersion": 2,
      "position": [
        1200,
        110
      ]
    },
    {
      "parameters": {
        "jsCode": "let url = '';\ntry { url = $('파라미터 파싱').first().json.url || ''; } catch {}\n\nreturn [{ json: {\n  ok: false,\n  mode: 'fallback',\n  url,\n  track: null,\n  message: 'BGM 정밀 식별 실패 — 오디오 클립 추출(yt-dlp/ffmpeg) 또는 AudD 호출 중 오류가 발생했습니다. n8n 컨테이너에 yt-dlp·ffmpeg가 설치되어 있는지, AUDD_API_TOKEN이 설정되어 있는지 확인하세요.',\n} }];"
      },
      "id": "node-fallback-bgm",
      "name": "폴백 (추출·인식 실패)",
      "type": "n8n-nodes-base.code",
      "typeVersion": 2,
      "position": [
        760,
        420
      ]
    }
  ],
  "connections": {
    "Webhook 수신": {
      "main": [
        [
          {
            "node": "파라미터 파싱",
            "type": "main",
            "index": 0
          }
        ]
      ]
    },
    "수동 실행": {
      "main": [
        [
          {
            "node": "파라미터 파싱",
            "type": "main",
            "index": 0
          }
        ]
      ]
    },
    "파라미터 파싱": {
      "main": [
        [
          {
            "node": "오디오 클립 추출 (yt-dlp+ffmpeg)",
            "type": "main",
            "index": 0
          }
        ]
      ]
    },
    "오디오 클립 추출 (yt-dlp+ffmpeg)": {
      "main": [
        [
          {
            "node": "오디오 파일 읽기",
            "type": "main",
            "index": 0
          }
        ],
        [
          {
            "node": "폴백 (추출·인식 실패)",
            "type": "main",
            "index": 0
          }
        ]
      ]
    },
    "오디오 파일 읽기": {
      "main": [
        [
          {
            "node": "AudD: 음향 지문 매칭",
            "type": "main",
            "index": 0
          }
        ],
        [
          {
            "node": "폴백 (추출·인식 실패)",
            "type": "main",
            "index": 0
          }
        ]
      ]
    },
    "AudD: 음향 지문 매칭": {
      "main": [
        [
          {
            "node": "AudD 결과 파싱",
            "type": "main",
            "index": 0
          }
        ],
        [
          {
            "node": "폴백 (추출·인식 실패)",
            "type": "main",
            "index": 0
          }
        ]
      ]
    },
    "AudD 결과 파싱": {
      "main": [
        []
      ]
    },
    "폴백 (추출·인식 실패)": {
      "main": [
        []
      ]
    }
  },
  "settings": {
    "executionOrder": "v1"
  },
  "staticData": null,
  "tags": [
    {
      "name": "콘텐츠 제작"
    },
    {
      "name": "BGM"
    }
  ],
  "pinData": {},
  "id": "Bgm1dent1fyAuD0"
}
