{
  "name": "아웃라이어 자동 태깅",
  "nodes": [
    {
      "parameters": {
        "httpMethod": "POST",
        "path": "outlier-tagging",
        "responseMode": "lastNode",
        "options": {}
      },
      "id": "node-webhook-outlier",
      "name": "Webhook 태깅",
      "type": "n8n-nodes-base.webhook",
      "typeVersion": 2,
      "position": [
        100,
        200
      ],
      "webhookId": "outlier-tagging-webhook"
    },
    {
      "parameters": {},
      "id": "node-manual-outlier",
      "name": "수동 실행",
      "type": "n8n-nodes-base.manualTrigger",
      "typeVersion": 1,
      "position": [
        100,
        380
      ]
    },
    {
      "parameters": {
        "rule": {
          "interval": [
            {
              "field": "days",
              "daysInterval": 1
            }
          ]
        }
      },
      "type": "n8n-nodes-base.scheduleTrigger",
      "typeVersion": 1.2,
      "id": "node-schedule-outlier",
      "name": "스케줄 (1일마다)",
      "position": [
        100,
        560
      ]
    },
    {
      "parameters": {
        "jsCode": "let minVsAvg = 3;\nlet persistTagged = true;\ntry {\n  const whItems = $('Webhook 태깅').all();\n  if (whItems.length) {\n    const raw = whItems[0].json;\n    const b = raw.body ?? raw;\n    const parsed = typeof b === 'string' ? JSON.parse(b) : b;\n    if (parsed?.minVsAvg != null) minVsAvg = Number(parsed.minVsAvg);\n    if (parsed?.persistTagged != null) persistTagged = Boolean(parsed.persistTagged);\n  }\n} catch {\n  /* manual / schedule defaults */\n}\nif (!Number.isFinite(minVsAvg) || minVsAvg <= 0) minVsAvg = 3;\nreturn [{ json: { minVsAvg, persistTagged, source: 'n8n' } }];"
      },
      "id": "node-parse-params",
      "name": "기준 설정",
      "type": "n8n-nodes-base.code",
      "typeVersion": 2,
      "position": [
        320,
        380
      ]
    },
    {
      "parameters": {
        "method": "GET",
        "url": "={{ $env.SUPABASE_URL }}/rest/v1/videos?vs_avg=gte.{{ $json.minVsAvg }}&select=video_id,title,channel_id,channel_name,platform,vs_avg,tier&order=vs_avg.desc&limit=100",
        "sendHeaders": true,
        "headerParameters": {
          "parameters": [
            {
              "name": "apikey",
              "value": "={{ $env.SUPABASE_SERVICE_KEY }}"
            },
            {
              "name": "Authorization",
              "value": "=Bearer {{ $env.SUPABASE_SERVICE_KEY }}"
            }
          ]
        },
        "options": {}
      },
      "id": "node-fetch-outliers",
      "name": "Supabase: Outlier 후보 조회",
      "type": "n8n-nodes-base.httpRequest",
      "typeVersion": 4.2,
      "position": [
        540,
        380
      ]
    },
    {
      "parameters": {
        "jsCode": "const params = $('기준 설정').first().json;\nconst minVsAvg = params.minVsAvg;\nconst persistTagged = params.persistTagged;\nconst source = params.source || 'n8n';\n\nconst items = $input.all();\nlet rows = [];\nconst j0 = items[0]?.json;\nif (items.length === 1 && Array.isArray(j0)) {\n  rows = j0;\n} else if (items.length >= 1 && j0 && typeof j0 === 'object' && !Array.isArray(j0) && j0.video_id) {\n  rows = items.map((i) => i.json).filter((r) => r?.video_id);\n} else if (items.length === 1 && j0 && Array.isArray(j0.data)) {\n  rows = j0.data;\n}\n\nif (!rows.length) {\n  return [{ json: {\n    ok: true,\n    minVsAvg,\n    candidateCount: 0,\n    taggedCount: 0,\n    tierUpdatedCount: 0,\n    message: `vs.Avg ${minVsAvg}x 이상 영상이 없습니다. YouTube 수집을 먼저 실행하세요.`,\n    skipSave: true,\n  } }];\n}\n\nconst now = new Date().toISOString();\nconst tierRank = { C: 0, B: 1, A: 2, S: 3 };\nconst tierFor = (v) => (v >= 5 ? 'S' : v >= 3 ? 'A' : v >= 1.5 ? 'B' : 'C');\n\nconst tagRows = rows.map((v) => ({\n  video_id: String(v.video_id),\n  title: String(v.title || '').slice(0, 500),\n  channel_id: v.channel_id ?? null,\n  channel_name: v.channel_name ?? null,\n  platform: v.platform || 'youtube',\n  vs_avg: Number(v.vs_avg ?? 0),\n  min_vs_avg_threshold: minVsAvg,\n  tagged_at: now,\n  source,\n  updated_at: now,\n}));\n\nif (!persistTagged) {\n  return [{ json: {\n    ok: true,\n    preview: true,\n    minVsAvg,\n    candidateCount: rows.length,\n    taggedCount: 0,\n    sample: tagRows.slice(0, 5),\n    message: `미리보기: ${rows.length}개 후보`,\n    skipSave: true,\n  } }];\n}\n\nreturn [{ json: {\n  ok: true,\n  minVsAvg,\n  candidateCount: rows.length,\n  tagRows,\n  skipSave: false,\n} }];"
      },
      "id": "node-build-tags",
      "name": "태그·Tier 목록 생성",
      "type": "n8n-nodes-base.code",
      "typeVersion": 2,
      "position": [
        760,
        380
      ]
    },
    {
      "parameters": {
        "conditions": {
          "options": {
            "caseSensitive": true,
            "leftValue": "",
            "typeValidation": "strict"
          },
          "conditions": [
            {
              "id": "skip-save",
              "leftValue": "={{ $json.skipSave }}",
              "rightValue": true,
              "operator": {
                "type": "boolean",
                "operation": "equals"
              }
            }
          ],
          "combinator": "and"
        },
        "options": {}
      },
      "id": "node-if-skip",
      "name": "저장 스킵?",
      "type": "n8n-nodes-base.if",
      "typeVersion": 2,
      "position": [
        980,
        380
      ]
    },
    {
      "parameters": {
        "method": "POST",
        "url": "={{ $env.SUPABASE_URL }}/rest/v1/outlier_tags?on_conflict=video_id",
        "sendHeaders": true,
        "headerParameters": {
          "parameters": [
            {
              "name": "apikey",
              "value": "={{ $env.SUPABASE_SERVICE_KEY }}"
            },
            {
              "name": "Authorization",
              "value": "=Bearer {{ $env.SUPABASE_SERVICE_KEY }}"
            },
            {
              "name": "Content-Type",
              "value": "application/json"
            },
            {
              "name": "Prefer",
              "value": "resolution=merge-duplicates,return=minimal"
            }
          ]
        },
        "sendBody": true,
        "contentType": "raw",
        "rawContentType": "application/json",
        "body": "={{ JSON.stringify($json.tagRows) }}",
        "options": {}
      },
      "id": "node-save-tags",
      "name": "Supabase: outlier_tags 저장",
      "type": "n8n-nodes-base.httpRequest",
      "typeVersion": 4.2,
      "position": [
        1200,
        280
      ]
    },
    {
      "parameters": {
        "jsCode": "const built = $('태그·Tier 목록 생성').first().json;\nconst count = (built.tagRows || []).length;\nreturn [{ json: {\n  ok: true,\n  mode: 'n8n',\n  minVsAvg: built.minVsAvg,\n  candidateCount: built.candidateCount,\n  taggedCount: count,\n  tierUpdatedCount: 0,\n  message: `아웃라이어 ${count}개 outlier_tags 저장 완료`,\n  timestamp: new Date().toISOString(),\n} }];"
      },
      "id": "node-done-save",
      "name": "완료 (저장)",
      "type": "n8n-nodes-base.code",
      "typeVersion": 2,
      "position": [
        1420,
        280
      ]
    },
    {
      "parameters": {
        "jsCode": "const built = $input.first().json;\nreturn [{ json: {\n  ok: built.ok !== false,\n  mode: 'n8n',\n  preview: built.preview === true,\n  minVsAvg: built.minVsAvg,\n  candidateCount: built.candidateCount ?? 0,\n  taggedCount: built.taggedCount ?? 0,\n  message: built.message,\n  timestamp: new Date().toISOString(),\n} }];"
      },
      "id": "node-done-skip",
      "name": "완료 (스킵/미리보기)",
      "type": "n8n-nodes-base.code",
      "typeVersion": 2,
      "position": [
        1200,
        480
      ]
    }
  ],
  "connections": {
    "Webhook 태깅": {
      "main": [
        [
          {
            "node": "기준 설정",
            "type": "main",
            "index": 0
          }
        ]
      ]
    },
    "수동 실행": {
      "main": [
        [
          {
            "node": "기준 설정",
            "type": "main",
            "index": 0
          }
        ]
      ]
    },
    "기준 설정": {
      "main": [
        [
          {
            "node": "Supabase: Outlier 후보 조회",
            "type": "main",
            "index": 0
          }
        ]
      ]
    },
    "Supabase: Outlier 후보 조회": {
      "main": [
        [
          {
            "node": "태그·Tier 목록 생성",
            "type": "main",
            "index": 0
          }
        ]
      ]
    },
    "태그·Tier 목록 생성": {
      "main": [
        [
          {
            "node": "저장 스킵?",
            "type": "main",
            "index": 0
          }
        ]
      ]
    },
    "저장 스킵?": {
      "main": [
        [
          {
            "node": "완료 (스킵/미리보기)",
            "type": "main",
            "index": 0
          }
        ],
        [
          {
            "node": "Supabase: outlier_tags 저장",
            "type": "main",
            "index": 0
          }
        ]
      ]
    },
    "Supabase: outlier_tags 저장": {
      "main": [
        [
          {
            "node": "완료 (저장)",
            "type": "main",
            "index": 0
          }
        ]
      ]
    },
    "스케줄 (1일마다)": {
      "main": [
        [
          {
            "node": "기준 설정",
            "type": "main",
            "index": 0
          }
        ]
      ]
    }
  },
  "settings": {
    "executionOrder": "v1"
  },
  "staticData": null,
  "tags": [
    {
      "name": "Outlier"
    }
  ],
  "pinData": {}
}
